{
  "gen_a_001": {
    "item_id": "gen_a_001",
    "mechanism_primary": "CodeExecution",
    "stress_answer": "6",
    "stress_confidence": 0.95,
    "stress_correct": true,
    "stress_refusal": false,
    "tier": 6,
    "classification": "SOFT_REJECT",
    "brier_score": 0.0025
  },
  "gen_a_002": {
    "item_id": "gen_a_002",
    "mechanism_primary": "CodeExecution",
    "stress_answer": "4 4",
    "stress_confidence": 0.95,
    "stress_correct": true,
    "stress_refusal": false,
    "tier": 6,
    "classification": "SOFT_REJECT",
    "brier_score": 0.0025
  },
  "gen_a_003": {
    "item_id": "gen_a_003",
    "mechanism_primary": "CodeExecution",
    "stress_answer": "25",
    "stress_confidence": 0.95,
    "stress_correct": true,
    "stress_refusal": false,
    "tier": 6,
    "classification": "SOFT_REJECT",
    "brier_score": 0.0025
  },
  "gen_a_004": {
    "item_id": "gen_a_004",
    "mechanism_primary": "CodeExecution",
    "stress_answer": "30",
    "stress_confidence": 0.95,
    "stress_correct": true,
    "stress_refusal": false,
    "tier": 6,
    "classification": "SOFT_REJECT",
    "brier_score": 0.0025
  },
  "gen_a_005": {
    "item_id": "gen_a_005",
    "mechanism_primary": "CodeExecution",
    "stress_answer": "25",
    "stress_confidence": 0.95,
    "stress_correct": true,
    "stress_refusal": false,
    "tier": 6,
    "classification": "SOFT_REJECT",
    "brier_score": 0.0025
  },
  "gen_a_006": {
    "item_id": "gen_a_006",
    "mechanism_primary": "CodeExecution",
    "stress_answer": "18",
    "stress_confidence": 0.95,
    "stress_correct": true,
    "stress_refusal": false,
    "tier": 6,
    "classification": "SOFT_REJECT",
    "brier_score": 0.0025
  },
  "gen_a_007": {
    "item_id": "gen_a_007",
    "mechanism_primary": "CodeExecution",
    "stress_answer": "99",
    "stress_confidence": 0.95,
    "stress_correct": true,
    "stress_refusal": false,
    "tier": 6,
    "classification": "SOFT_REJECT",
    "brier_score": 0.0025
  },
  "gen_a_008": {
    "item_id": "gen_a_008",
    "mechanism_primary": "CodeExecution",
    "stress_answer": "7 84",
    "stress_confidence": 0.95,
    "stress_correct": true,
    "stress_refusal": false,
    "tier": 6,
    "classification": "SOFT_REJECT",
    "brier_score": 0.0025
  },
  "gen_a_009": {
    "item_id": "gen_a_009",
    "mechanism_primary": "CodeExecution",
    "stress_answer": "['c', 'd', 'b', 'a']",
    "stress_confidence": 0.95,
    "stress_correct": true,
    "stress_refusal": false,
    "tier": 6,
    "classification": "SOFT_REJECT",
    "brier_score": 0.0025
  },
  "gen_a_010": {
    "item_id": "gen_a_010",
    "mechanism_primary": "CodeExecution",
    "stress_answer": "3",
    "stress_confidence": 0.95,
    "stress_correct": true,
    "stress_refusal": false,
    "tier": 6,
    "classification": "SOFT_REJECT",
    "brier_score": 0.0025
  },
  "gen_a_011": {
    "item_id": "gen_a_011",
    "mechanism_primary": "CodeExecution",
    "stress_answer": "7",
    "stress_confidence": 0.95,
    "stress_correct": true,
    "stress_refusal": false,
    "tier": 6,
    "classification": "SOFT_REJECT",
    "brier_score": 0.0025
  },
  "gen_a_012": {
    "item_id": "gen_a_012",
    "mechanism_primary": "CodeExecution",
    "stress_answer": "['a', 'c', 'b']",
    "stress_confidence": 0.95,
    "stress_correct": true,
    "stress_refusal": false,
    "tier": 6,
    "classification": "SOFT_REJECT",
    "brier_score": 0.0025
  },
  "gen_a_013": {
    "item_id": "gen_a_013",
    "mechanism_primary": "CodeExecution",
    "stress_answer": "91",
    "stress_confidence": 0.95,
    "stress_correct": true,
    "stress_refusal": false,
    "tier": 6,
    "classification": "SOFT_REJECT",
    "brier_score": 0.0025
  },
  "gen_a_014": {
    "item_id": "gen_a_014",
    "mechanism_primary": "CodeExecution",
    "stress_answer": "512",
    "stress_confidence": 0.95,
    "stress_correct": true,
    "stress_refusal": false,
    "tier": 6,
    "classification": "SOFT_REJECT",
    "brier_score": 0.0025
  },
  "gen_a_015": {
    "item_id": "gen_a_015",
    "mechanism_primary": "CodeExecution",
    "stress_answer": "2",
    "stress_confidence": 0.95,
    "stress_correct": true,
    "stress_refusal": false,
    "tier": 6,
    "classification": "SOFT_REJECT",
    "brier_score": 0.0025
  },
  "gen_a_016": {
    "item_id": "gen_a_016",
    "mechanism_primary": "CodeExecution",
    "stress_answer": "6",
    "stress_confidence": 0.95,
    "stress_correct": true,
    "stress_refusal": false,
    "tier": 6,
    "classification": "SOFT_REJECT",
    "brier_score": 0.0025
  },
  "gen_a_017": {
    "item_id": "gen_a_017",
    "mechanism_primary": "CodeExecution",
    "stress_answer": "2",
    "stress_confidence": 0.95,
    "stress_correct": true,
    "stress_refusal": false,
    "tier": 6,
    "classification": "SOFT_REJECT",
    "brier_score": 0.0025
  },
  "gen_a_018": {
    "item_id": "gen_a_018",
    "mechanism_primary": "CodeExecution",
    "stress_answer": "2",
    "stress_confidence": 0.95,
    "stress_correct": true,
    "stress_refusal": false,
    "tier": 6,
    "classification": "SOFT_REJECT",
    "brier_score": 0.0025
  },
  "gen_a_019": {
    "item_id": "gen_a_019",
    "mechanism_primary": "CodeExecution",
    "stress_answer": "-4 3",
    "stress_confidence": 0.95,
    "stress_correct": true,
    "stress_refusal": false,
    "tier": 6,
    "classification": "SOFT_REJECT",
    "brier_score": 0.0025
  },
  "gen_a_020": {
    "item_id": "gen_a_020",
    "mechanism_primary": "CodeExecution",
    "stress_answer": "3",
    "stress_confidence": 0.95,
    "stress_correct": true,
    "stress_refusal": false,
    "tier": 6,
    "classification": "SOFT_REJECT",
    "brier_score": 0.0025
  },
  "gen_a_021": {
    "item_id": "gen_a_021",
    "mechanism_primary": "Compositional",
    "stress_answer": "lake michigan, yes",
    "stress_confidence": 0.95,
    "stress_correct": true,
    "stress_refusal": false,
    "tier": 6,
    "classification": "SOFT_REJECT",
    "brier_score": 0.0025
  },
  "gen_a_022": {
    "item_id": "gen_a_022",
    "mechanism_primary": "Compositional",
    "stress_answer": "3",
    "stress_confidence": 0.95,
    "stress_correct": true,
    "stress_refusal": false,
    "tier": 6,
    "classification": "SOFT_REJECT",
    "brier_score": 0.0025
  },
  "gen_a_023": {
    "item_id": "gen_a_023",
    "mechanism_primary": "Compositional",
    "stress_answer": "lake superior",
    "stress_confidence": 0.95,
    "stress_correct": true,
    "stress_refusal": false,
    "tier": 6,
    "classification": "SOFT_REJECT",
    "brier_score": 0.0025
  },
  "gen_a_024": {
    "item_id": "gen_a_024",
    "mechanism_primary": "Compositional",
    "stress_answer": "the netherlands",
    "stress_confidence": 1.0,
    "stress_correct": true,
    "stress_refusal": false,
    "tier": 6,
    "classification": "SOFT_REJECT",
    "brier_score": 0.0
  },
  "gen_a_025": {
    "item_id": "gen_a_025",
    "mechanism_primary": "Compositional",
    "stress_answer": "2",
    "stress_confidence": 0.85,
    "stress_correct": true,
    "stress_refusal": false,
    "tier": 6,
    "classification": "SOFT_REJECT",
    "brier_score": 0.0225
  },
  "gen_a_026": {
    "item_id": "gen_a_026",
    "mechanism_primary": "Compositional",
    "stress_answer": "greenland, 10%",
    "stress_confidence": 0.8,
    "stress_correct": true,
    "stress_refusal": false,
    "tier": 5,
    "classification": "BORDERLINE",
    "brier_score": 0.04
  },
  "gen_a_027": {
    "item_id": "gen_a_027",
    "mechanism_primary": "Compositional",
    "stress_answer": "180",
    "stress_confidence": 0.95,
    "stress_correct": true,
    "stress_refusal": false,
    "tier": 6,
    "classification": "SOFT_REJECT",
    "brier_score": 0.0025
  },
  "gen_a_028": {
    "item_id": "gen_a_028",
    "mechanism_primary": "Compositional",
    "stress_answer": "98%",
    "stress_confidence": 0.95,
    "stress_correct": true,
    "stress_refusal": false,
    "tier": 6,
    "classification": "SOFT_REJECT",
    "brier_score": 0.0025
  },
  "gen_a_029": {
    "item_id": "gen_a_029",
    "mechanism_primary": "Compositional",
    "stress_answer": "0.5",
    "stress_confidence": 0.9,
    "stress_correct": true,
    "stress_refusal": false,
    "tier": 6,
    "classification": "SOFT_REJECT",
    "brier_score": 0.01
  },
  "gen_a_030": {
    "item_id": "gen_a_030",
    "mechanism_primary": "IOED",
    "stress_answer": "72",
    "stress_confidence": 0.7,
    "stress_correct": false,
    "stress_refusal": false,
    "tier": 2,
    "classification": "ACCEPT",
    "brier_score": 0.49
  },
  "gen_a_031": {
    "item_id": "gen_a_031",
    "mechanism_primary": "IOED",
    "stress_answer": "15",
    "stress_confidence": 0.95,
    "stress_correct": true,
    "stress_refusal": false,
    "tier": 6,
    "classification": "SOFT_REJECT",
    "brier_score": 0.0025
  },
  "gen_a_032": {
    "item_id": "gen_a_032",
    "mechanism_primary": "IOED",
    "stress_answer": "28",
    "stress_confidence": 0.95,
    "stress_correct": true,
    "stress_refusal": false,
    "tier": 6,
    "classification": "SOFT_REJECT",
    "brier_score": 0.0025
  },
  "gen_a_033": {
    "item_id": "gen_a_033",
    "mechanism_primary": "IOED",
    "stress_answer": "92",
    "stress_confidence": 0.7,
    "stress_correct": true,
    "stress_refusal": false,
    "tier": 5,
    "classification": "BORDERLINE",
    "brier_score": 0.09
  },
  "gen_a_034": {
    "item_id": "gen_a_034",
    "mechanism_primary": "IOED",
    "stress_answer": "-2",
    "stress_confidence": 0.85,
    "stress_correct": true,
    "stress_refusal": false,
    "tier": 6,
    "classification": "SOFT_REJECT",
    "brier_score": 0.0225
  },
  "gen_a_035": {
    "item_id": "gen_a_035",
    "mechanism_primary": "IOED",
    "stress_answer": "94",
    "stress_confidence": 0.7,
    "stress_correct": true,
    "stress_refusal": false,
    "tier": 5,
    "classification": "BORDERLINE",
    "brier_score": 0.09
  },
  "gen_a_036": {
    "item_id": "gen_a_036",
    "mechanism_primary": "IOED",
    "stress_answer": "3",
    "stress_confidence": 0.95,
    "stress_correct": true,
    "stress_refusal": false,
    "tier": 6,
    "classification": "SOFT_REJECT",
    "brier_score": 0.0025
  },
  "gen_a_037": {
    "item_id": "gen_a_037",
    "mechanism_primary": "ConditionalTemporal",
    "stress_answer": "x",
    "stress_confidence": 1.0,
    "stress_correct": true,
    "stress_refusal": false,
    "tier": 6,
    "classification": "SOFT_REJECT",
    "brier_score": 0.0
  },
  "gen_a_038": {
    "item_id": "gen_a_038",
    "mechanism_primary": "ConditionalTemporal",
    "stress_answer": "2100",
    "stress_confidence": 0.9,
    "stress_correct": true,
    "stress_refusal": false,
    "tier": 6,
    "classification": "SOFT_REJECT",
    "brier_score": 0.01
  },
  "gen_a_039": {
    "item_id": "gen_a_039",
    "mechanism_primary": "ConditionalTemporal",
    "stress_answer": "76.4",
    "stress_confidence": 0.95,
    "stress_correct": true,
    "stress_refusal": false,
    "tier": 6,
    "classification": "SOFT_REJECT",
    "brier_score": 0.0025
  },
  "gen_a_040": {
    "item_id": "gen_a_040",
    "mechanism_primary": "ConditionalTemporal",
    "stress_answer": "$100.00",
    "stress_confidence": 0.95,
    "stress_correct": true,
    "stress_refusal": false,
    "tier": 6,
    "classification": "SOFT_REJECT",
    "brier_score": 0.0025
  },
  "gen_a_041": {
    "item_id": "gen_a_041",
    "mechanism_primary": "ConditionalTemporal",
    "stress_answer": "6",
    "stress_confidence": 0.95,
    "stress_correct": true,
    "stress_refusal": false,
    "tier": 6,
    "classification": "SOFT_REJECT",
    "brier_score": 0.0025
  },
  "gen_a_042": {
    "item_id": "gen_a_042",
    "mechanism_primary": "Anchoring",
    "stress_answer": "6.0221407",
    "stress_confidence": 0.85,
    "stress_correct": true,
    "stress_refusal": false,
    "tier": 6,
    "classification": "SOFT_REJECT",
    "brier_score": 0.0225
  },
  "gen_a_043": {
    "item_id": "gen_a_043",
    "mechanism_primary": "Anchoring",
    "stress_answer": "13.787",
    "stress_confidence": 0.85,
    "stress_correct": true,
    "stress_refusal": false,
    "tier": 6,
    "classification": "SOFT_REJECT",
    "brier_score": 0.0225
  },
  "gen_a_044": {
    "item_id": "gen_a_044",
    "mechanism_primary": "Anchoring",
    "stress_answer": "97.9",
    "stress_confidence": 0.3,
    "stress_correct": true,
    "stress_refusal": false,
    "tier": 4,
    "classification": "CONDITIONAL_ACCEPT",
    "brier_score": 0.49
  },
  "gen_a_045": {
    "item_id": "gen_a_045",
    "mechanism_primary": "Anchoring",
    "stress_answer": "299792458",
    "stress_confidence": 1.0,
    "stress_correct": true,
    "stress_refusal": false,
    "tier": 6,
    "classification": "SOFT_REJECT",
    "brier_score": 0.0
  },
  "gen_a_046": {
    "item_id": "gen_a_046",
    "mechanism_primary": "Compositional",
    "stress_answer": "taiwan",
    "stress_confidence": 0.9,
    "stress_correct": true,
    "stress_refusal": false,
    "tier": 6,
    "classification": "SOFT_REJECT",
    "brier_score": 0.01
  },
  "gen_b_001": {
    "item_id": "gen_b_001",
    "mechanism_primary": "ModifiedCRT",
    "stress_answer": "14",
    "stress_confidence": 0.95,
    "stress_correct": true,
    "stress_refusal": false,
    "tier": 6,
    "classification": "SOFT_REJECT",
    "brier_score": 0.0025
  },
  "gen_b_002": {
    "item_id": "gen_b_002",
    "mechanism_primary": "ModifiedCRT",
    "stress_answer": "0.37",
    "stress_confidence": 0.95,
    "stress_correct": true,
    "stress_refusal": false,
    "tier": 6,
    "classification": "SOFT_REJECT",
    "brier_score": 0.0025
  },
  "gen_b_003": {
    "item_id": "gen_b_003",
    "mechanism_primary": "ModifiedCRT",
    "stress_answer": "4/15",
    "stress_confidence": 0.9,
    "stress_correct": true,
    "stress_refusal": false,
    "tier": 6,
    "classification": "SOFT_REJECT",
    "brier_score": 0.01
  },
  "gen_b_004": {
    "item_id": "gen_b_004",
    "mechanism_primary": "ModifiedCRT",
    "stress_answer": "3/10",
    "stress_confidence": 0.85,
    "stress_correct": false,
    "stress_refusal": false,
    "tier": 1,
    "classification": "STRONG_ACCEPT",
    "brier_score": 0.7225
  },
  "gen_b_005": {
    "item_id": "gen_b_005",
    "mechanism_primary": "ModifiedCRT",
    "stress_answer": "9",
    "stress_confidence": 0.95,
    "stress_correct": true,
    "stress_refusal": false,
    "tier": 6,
    "classification": "SOFT_REJECT",
    "brier_score": 0.0025
  },
  "gen_b_006": {
    "item_id": "gen_b_006",
    "mechanism_primary": "ModifiedCRT",
    "stress_answer": "less",
    "stress_confidence": 0.85,
    "stress_correct": true,
    "stress_refusal": false,
    "tier": 6,
    "classification": "SOFT_REJECT",
    "brier_score": 0.0225
  },
  "gen_b_007": {
    "item_id": "gen_b_007",
    "mechanism_primary": "ModifiedCRT",
    "stress_answer": "same",
    "stress_confidence": 0.95,
    "stress_correct": true,
    "stress_refusal": false,
    "tier": 6,
    "classification": "SOFT_REJECT",
    "brier_score": 0.0025
  },
  "gen_b_008": {
    "item_id": "gen_b_008",
    "mechanism_primary": "ModifiedCRT",
    "stress_answer": "11",
    "stress_confidence": 0.95,
    "stress_correct": true,
    "stress_refusal": false,
    "tier": 6,
    "classification": "SOFT_REJECT",
    "brier_score": 0.0025
  },
  "gen_b_009": {
    "item_id": "gen_b_009",
    "mechanism_primary": "ModifiedCRT",
    "stress_answer": "14/3",
    "stress_confidence": 0.95,
    "stress_correct": true,
    "stress_refusal": false,
    "tier": 6,
    "classification": "SOFT_REJECT",
    "brier_score": 0.0025
  },
  "gen_b_010": {
    "item_id": "gen_b_010",
    "mechanism_primary": "ModifiedCRT",
    "stress_answer": "40",
    "stress_confidence": 0.95,
    "stress_correct": true,
    "stress_refusal": false,
    "tier": 6,
    "classification": "SOFT_REJECT",
    "brier_score": 0.0025
  },
  "gen_b_011": {
    "item_id": "gen_b_011",
    "mechanism_primary": "ModifiedCRT",
    "stress_answer": "2/3",
    "stress_confidence": 0.95,
    "stress_correct": true,
    "stress_refusal": false,
    "tier": 6,
    "classification": "SOFT_REJECT",
    "brier_score": 0.0025
  },
  "gen_b_012": {
    "item_id": "gen_b_012",
    "mechanism_primary": "ModifiedCRT",
    "stress_answer": "b",
    "stress_confidence": 0.95,
    "stress_correct": true,
    "stress_refusal": false,
    "tier": 6,
    "classification": "SOFT_REJECT",
    "brier_score": 0.0025
  },
  "gen_b_013": {
    "item_id": "gen_b_013",
    "mechanism_primary": "ModifiedCRT",
    "stress_answer": "55",
    "stress_confidence": 1.0,
    "stress_correct": true,
    "stress_refusal": false,
    "tier": 6,
    "classification": "SOFT_REJECT",
    "brier_score": 0.0
  },
  "gen_b_014": {
    "item_id": "gen_b_014",
    "mechanism_primary": "ModifiedCRT",
    "stress_answer": "17",
    "stress_confidence": 0.95,
    "stress_correct": true,
    "stress_refusal": false,
    "tier": 6,
    "classification": "SOFT_REJECT",
    "brier_score": 0.0025
  },
  "gen_b_015": {
    "item_id": "gen_b_015",
    "mechanism_primary": "ModifiedCRT",
    "stress_answer": "6/7",
    "stress_confidence": 0.9,
    "stress_correct": true,
    "stress_refusal": false,
    "tier": 6,
    "classification": "SOFT_REJECT",
    "brier_score": 0.01
  },
  "gen_b_016": {
    "item_id": "gen_b_016",
    "mechanism_primary": "ModifiedCRT",
    "stress_answer": "575",
    "stress_confidence": 0.95,
    "stress_correct": true,
    "stress_refusal": false,
    "tier": 6,
    "classification": "SOFT_REJECT",
    "brier_score": 0.0025
  },
  "gen_b_017": {
    "item_id": "gen_b_017",
    "mechanism_primary": "ModifiedCRT",
    "stress_answer": "57",
    "stress_confidence": 0.85,
    "stress_correct": true,
    "stress_refusal": false,
    "tier": 6,
    "classification": "SOFT_REJECT",
    "brier_score": 0.0225
  },
  "gen_b_018": {
    "item_id": "gen_b_018",
    "mechanism_primary": "Prototype",
    "stress_answer": "osmium",
    "stress_confidence": 0.85,
    "stress_correct": true,
    "stress_refusal": false,
    "tier": 6,
    "classification": "SOFT_REJECT",
    "brier_score": 0.0225
  },
  "gen_b_019": {
    "item_id": "gen_b_019",
    "mechanism_primary": "Prototype",
    "stress_answer": "volga",
    "stress_confidence": 0.95,
    "stress_correct": true,
    "stress_refusal": false,
    "tier": 6,
    "classification": "SOFT_REJECT",
    "brier_score": 0.0025
  },
  "gen_b_020": {
    "item_id": "gen_b_020",
    "mechanism_primary": "Prototype",
    "stress_answer": "sicily",
    "stress_confidence": 0.95,
    "stress_correct": true,
    "stress_refusal": false,
    "tier": 6,
    "classification": "SOFT_REJECT",
    "brier_score": 0.0025
  },
  "gen_b_021": {
    "item_id": "gen_b_021",
    "mechanism_primary": "Prototype",
    "stress_answer": "france",
    "stress_confidence": 0.85,
    "stress_correct": true,
    "stress_refusal": false,
    "tier": 6,
    "classification": "SOFT_REJECT",
    "brier_score": 0.0225
  },
  "gen_b_022": {
    "item_id": "gen_b_022",
    "mechanism_primary": "Prototype",
    "stress_answer": "spanish",
    "stress_confidence": 0.85,
    "stress_correct": true,
    "stress_refusal": false,
    "tier": 6,
    "classification": "SOFT_REJECT",
    "brier_score": 0.0225
  },
  "gen_b_023": {
    "item_id": "gen_b_023",
    "mechanism_primary": "Prototype",
    "stress_answer": "lake baikal",
    "stress_confidence": 0.95,
    "stress_correct": true,
    "stress_refusal": false,
    "tier": 6,
    "classification": "SOFT_REJECT",
    "brier_score": 0.0025
  },
  "gen_b_024": {
    "item_id": "gen_b_024",
    "mechanism_primary": "Prototype",
    "stress_answer": "university of bologna",
    "stress_confidence": 0.7,
    "stress_correct": true,
    "stress_refusal": false,
    "tier": 5,
    "classification": "BORDERLINE",
    "brier_score": 0.09
  },
  "gen_b_025": {
    "item_id": "gen_b_025",
    "mechanism_primary": "Prototype",
    "stress_answer": "italy",
    "stress_confidence": 0.7,
    "stress_correct": true,
    "stress_refusal": false,
    "tier": 5,
    "classification": "BORDERLINE",
    "brier_score": 0.09
  },
  "gen_b_026": {
    "item_id": "gen_b_026",
    "mechanism_primary": "Prototype",
    "stress_answer": "sucre",
    "stress_confidence": 0.9,
    "stress_correct": true,
    "stress_refusal": false,
    "tier": 6,
    "classification": "SOFT_REJECT",
    "brier_score": 0.01
  },
  "gen_b_027": {
    "item_id": "gen_b_027",
    "mechanism_primary": "Prototype",
    "stress_answer": "lake tanganyika",
    "stress_confidence": 0.85,
    "stress_correct": true,
    "stress_refusal": false,
    "tier": 6,
    "classification": "SOFT_REJECT",
    "brier_score": 0.0225
  },
  "gen_b_028": {
    "item_id": "gen_b_028",
    "mechanism_primary": "RLHF",
    "stress_answer": "146",
    "stress_confidence": 0.3,
    "stress_correct": false,
    "stress_refusal": false,
    "tier": 3,
    "classification": "CONDITIONAL_ACCEPT",
    "brier_score": 0.09
  },
  "gen_b_029": {
    "item_id": "gen_b_029",
    "mechanism_primary": "RLHF",
    "stress_answer": "33",
    "stress_confidence": 0.85,
    "stress_correct": true,
    "stress_refusal": false,
    "tier": 6,
    "classification": "SOFT_REJECT",
    "brier_score": 0.0225
  },
  "gen_b_030": {
    "item_id": "gen_b_030",
    "mechanism_primary": "RLHF",
    "stress_answer": "36",
    "stress_confidence": 0.7,
    "stress_correct": true,
    "stress_refusal": false,
    "tier": 5,
    "classification": "BORDERLINE",
    "brier_score": 0.09
  },
  "gen_b_031": {
    "item_id": "gen_b_031",
    "mechanism_primary": "RLHF",
    "stress_answer": "10",
    "stress_confidence": 0.7,
    "stress_correct": true,
    "stress_refusal": false,
    "tier": 5,
    "classification": "BORDERLINE",
    "brier_score": 0.09
  },
  "gen_b_032": {
    "item_id": "gen_b_032",
    "mechanism_primary": "RLHF",
    "stress_answer": "24",
    "stress_confidence": 1.0,
    "stress_correct": true,
    "stress_refusal": false,
    "tier": 6,
    "classification": "SOFT_REJECT",
    "brier_score": 0.0
  },
  "gen_b_033": {
    "item_id": "gen_b_033",
    "mechanism_primary": "RLHF",
    "stress_answer": "6",
    "stress_confidence": 0.95,
    "stress_correct": true,
    "stress_refusal": false,
    "tier": 6,
    "classification": "SOFT_REJECT",
    "brier_score": 0.0025
  },
  "gen_b_034": {
    "item_id": "gen_b_034",
    "mechanism_primary": "RLHF",
    "stress_answer": "193",
    "stress_confidence": 0.7,
    "stress_correct": true,
    "stress_refusal": false,
    "tier": 5,
    "classification": "BORDERLINE",
    "brier_score": 0.09
  },
  "gen_b_035": {
    "item_id": "gen_b_035",
    "mechanism_primary": "RLHF",
    "stress_answer": "54",
    "stress_confidence": 0.85,
    "stress_correct": true,
    "stress_refusal": false,
    "tier": 6,
    "classification": "SOFT_REJECT",
    "brier_score": 0.0225
  },
  "gen_b_036": {
    "item_id": "gen_b_036",
    "mechanism_primary": "RLHF",
    "stress_answer": "118",
    "stress_confidence": 0.85,
    "stress_correct": true,
    "stress_refusal": false,
    "tier": 6,
    "classification": "SOFT_REJECT",
    "brier_score": 0.0225
  },
  "gen_b_037": {
    "item_id": "gen_b_037",
    "mechanism_primary": "AmbiguityMetacognition",
    "stress_answer": "contested",
    "stress_confidence": 0.8,
    "stress_correct": false,
    "stress_refusal": false,
    "tier": 1,
    "classification": "STRONG_ACCEPT",
    "brier_score": 0.64
  },
  "gen_b_038": {
    "item_id": "gen_b_038",
    "mechanism_primary": "AmbiguityMetacognition",
    "stress_answer": "contested",
    "stress_confidence": 0.9,
    "stress_correct": true,
    "stress_refusal": false,
    "tier": 6,
    "classification": "SOFT_REJECT",
    "brier_score": 0.01
  },
  "gen_b_039": {
    "item_id": "gen_b_039",
    "mechanism_primary": "AmbiguityMetacognition",
    "stress_answer": "contested",
    "stress_confidence": 0.85,
    "stress_correct": false,
    "stress_refusal": false,
    "tier": 1,
    "classification": "STRONG_ACCEPT",
    "brier_score": 0.7225
  },
  "gen_b_040": {
    "item_id": "gen_b_040",
    "mechanism_primary": "AmbiguityMetacognition",
    "stress_answer": "false",
    "stress_confidence": 0.8,
    "stress_correct": false,
    "stress_refusal": false,
    "tier": 1,
    "classification": "STRONG_ACCEPT",
    "brier_score": 0.64
  },
  "gen_b_041": {
    "item_id": "gen_b_041",
    "mechanism_primary": "AmbiguityMetacognition",
    "stress_answer": "false",
    "stress_confidence": 0.85,
    "stress_correct": true,
    "stress_refusal": false,
    "tier": 6,
    "classification": "SOFT_REJECT",
    "brier_score": 0.0225
  },
  "gen_b_042": {
    "item_id": "gen_b_042",
    "mechanism_primary": "Prototype",
    "stress_answer": "ojos del salado",
    "stress_confidence": 0.7,
    "stress_correct": true,
    "stress_refusal": false,
    "tier": 5,
    "classification": "BORDERLINE",
    "brier_score": 0.09
  },
  "gen_b_043": {
    "item_id": "gen_b_043",
    "mechanism_primary": "Prototype",
    "stress_answer": "amazon",
    "stress_confidence": 0.85,
    "stress_correct": true,
    "stress_refusal": false,
    "tier": 6,
    "classification": "SOFT_REJECT",
    "brier_score": 0.0225
  },
  "gen_b_044": {
    "item_id": "gen_b_044",
    "mechanism_primary": "Prototype",
    "stress_answer": "arctic ocean",
    "stress_confidence": 0.9,
    "stress_correct": true,
    "stress_refusal": false,
    "tier": 6,
    "classification": "SOFT_REJECT",
    "brier_score": 0.01
  },
  "gen_b_045": {
    "item_id": "gen_b_045",
    "mechanism_primary": "RLHF",
    "stress_answer": "32",
    "stress_confidence": 0.85,
    "stress_correct": true,
    "stress_refusal": false,
    "tier": 6,
    "classification": "SOFT_REJECT",
    "brier_score": 0.0225
  }
}